macauff/perturbation_auf_fortran.cpython-311-darwin.so
macauff/galaxy_counts.py
macauff/shared_library.f90
macauff/misc_functions_fortran.f90
macauff/counterpart_pairing.py
macauff/photometric_likelihood.py
macauff/__init__.py
macauff/group_sources_fortran.f90
macauff/matching.py
macauff/group_sources.py
macauff/parse_catalogue.py
macauff/derive_psf_auf_params.py
macauff/counterpart_pairing_fortran.f90
macauff/counterpart_pairing_fortran.cpython-311-darwin.so
macauff/perturbation_auf.py
macauff/photometric_likelihood_fortran.cpython-311-darwin.so
macauff/fit_astrometry.py
macauff/photometric_likelihood_fortran.f90
macauff/make_set_list.py
macauff/misc_functions.py
macauff/galactic_proper_motions.py
macauff/group_sources_fortran.cpython-311-darwin.so
macauff/misc_functions_fortran.cpython-311-darwin.so
macauff/perturbation_auf_fortran.f90
macauff/get_trilegal_wrapper.py
macauff/tests/test_misc_functions.py
macauff/tests/test_counterpart_pairing.py
macauff/tests/test_fit_astrometry.py
macauff/tests/test_galaxy_counts.py
macauff/tests/test_parse_catalogue.py
macauff/tests/test_derive_psf_auf_params.py
macauff/tests/test_get_trilegal_wrapper.py
macauff/tests/__init__.py
macauff/tests/test_perturbation_auf.py
macauff/tests/test_full_match_process.py
macauff/tests/test_group_sources.py
macauff/tests/test_shared_library.py
macauff/tests/test_matching.py
macauff/tests/test_photometric_likelihood.py
macauff/tests/test_make_set_list.py
macauff/tests/data/cat_b_params.txt
macauff/tests/data/SFD_dust_4096_sgp.fits
macauff/tests/data/crossmatch_params.txt
macauff/tests/data/SFD_dust_4096_ngp.fits
macauff/tests/data/dd_params.npy
macauff/tests/data/cat_a_params.txt
macauff/tests/data/l_cut.npy
macauff/.dylibs/libgfortran.5.dylib
macauff/.dylibs/libquadmath.0.dylib
macauff/.dylibs/libgcc_s.1.1.dylib
macauff/.dylibs/libgomp.1.dylib
macauff-0.1.2.dist-info/RECORD
macauff-0.1.2.dist-info/WHEEL
macauff-0.1.2.dist-info/entry_points.txt
macauff-0.1.2.dist-info/METADATA
macauff-0.1.2.dist-info/licenses/LICENSE
