Metadata-Version: 2.1
Name: macauff
Version: 0.1.2
Requires-Python: >=3.8
Requires-Dist: astropy
Requires-Dist: matplotlib
Requires-Dist: numpy>=1.21
Requires-Dist: pandas
Requires-Dist: skypy
Requires-Dist: speclite
Requires-Dist: pytest-astropy; extra == "test"
Requires-Dist: scipy; extra == "test"
Requires-Dist: sphinx-astropy; extra == "docs"
Requires-Dist: sphinx-fortran; extra == "docs"
Requires-Dist: six; extra == "docs"
Provides-Extra: test
Provides-Extra: docs
